GhostDB/__init__.py
GhostDB/avl_tree.py
GhostDB/cache.py
GhostDB/ring.py
GhostDB/virtual_point.py
GhostDB/tests/ghostdb_sim.conf
GhostDB/tests/ghostdb_test.conf
ghostdb-0.9.dist-info/METADATA
ghostdb-0.9.dist-info/WHEEL
ghostdb-0.9.dist-info/top_level.txt
ghostdb-0.9.dist-info/RECORD
