Metadata-Version: 2.1
Name: ghostdb
Version: 0.9
Summary: Python SDK for GhostDB Cache
Home-page: UNKNOWN
Author: Jake Grogan
Author-email: jake.grogan8@mail.dcu.ie
License: MIT
Platform: UNKNOWN
Requires-Dist: requests
